[
    {
        "fileName": "6-for-6-y-u-qt-bootleg-scdler",
        "bpm": 133,
        "singer": "femme"
    },
    {
        "fileName": "actin-39-shady-scdler",
        "bpm": 109,
        "singer": "femme"
    },
    {
        "fileName": "all-around-me-scdler",
        "bpm": 66,
        "singer": "femme"
    },
    {
        "fileName": "alok-ella-eyre-amp-kenny-dope-feat.never-dull-deep-down-scdler",
        "bpm": 126,
        "singer": "femme"
    },
    {
        "fileName": "aza-our-time-jungle-edit-scdler",
        "bpm": 156,
        "singer": "femme"
    },
    {
        "fileName": "bet-you-never-scdler",
        "bpm": 159,
        "singer": "femme"
    },
    {
        "fileName": "blessing-in-this-house-higgo-remix-scdler",
        "bpm": 132,
        "singer": "femme"
    },
    {
        "fileName": "champion-sound-vip-scdler",
        "bpm": 140,
        "singer": "femme"
    },
    {
        "fileName": "crush-ft.driia-amp-naike-scdler",
        "bpm": 105,
        "singer": "femme"
    },
    {
        "fileName": "cutty-dub-23-scdler",
        "bpm": 140,
        "singer": "femme"
    },
    {
        "fileName": "dancehall-damager-feat.riko-dan-scdler",
        "bpm": 137,
        "singer": "femme"
    },
    {
        "fileName": "disclosure-higher-than-ever-before-dan-bemix-scdler",
        "bpm": 122,
        "singer": "femme"
    },
    {
        "fileName": "dj-s.k.t-amp-jem-cooke-boomerang-round-amp-round-higgo-remix-scdler",
        "bpm": 124,
        "singer": "femme"
    },
    {
        "fileName": "don-39-t-hesitate-scdler",
        "bpm": 145,
        "singer": "femme"
    },
    {
        "fileName": "don-39-t-wanna-be-talking-scdler",
        "bpm": 130,
        "singer": "femme"
    },
    {
        "fileName": "dream-theme-original-mix-scdler",
        "bpm": 91,
        "singer": "femme"
    },
    {
        "fileName": "drive-scdler",
        "bpm": 150,
        "singer": "femme"
    },
    {
        "fileName": "feels-like-summer-scdler",
        "bpm": 130,
        "singer": "femme"
    },
    {
        "fileName": "find-my-way-home-uk-garage-free-download-scdler",
        "bpm": 135,
        "singer": "femme"
    },
    {
        "fileName": "fontaines-dc-starburster-y-u-qt-dub-scdler",
        "bpm": 138,
        "singer": "femme"
    },
    {
        "fileName": "givemeafeeling-scdler",
        "bpm": 136,
        "singer": "femme"
    },
    {
        "fileName": "graace-21st-century-love-douvelle19-remix-scdler",
        "bpm": 124,
        "singer": "femme"
    },
    {
        "fileName": "hard-dub-scdler",
        "bpm": 139,
        "singer": "femme"
    },
    {
        "fileName": "here-goes-scdler",
        "bpm": 136,
        "singer": "femme"
    },
    {
        "fileName": "higgo-x-jill-scott-living-my-life-golden-scdler",
        "bpm": 128,
        "singer": "femme"
    },
    {
        "fileName": "higgo-x-lauren-l-39-aimant-sunshine-scdler",
        "bpm": 138,
        "singer": "femme"
    },
    {
        "fileName": "higgo-x-mustbejohn-i-just-wanna-dance-scdler",
        "bpm": 132,
        "singer": "femme"
    },
    {
        "fileName": "higgo-x-piri-think-twice-scdler",
        "bpm": 105,
        "singer": "femme"
    },
    {
        "fileName": "homeless-dub-scdler",
        "bpm": 130,
        "singer": "femme"
    },
    {
        "fileName": "i-know-scdler",
        "bpm": 90,
        "singer": "femme"
    },
    {
        "fileName": "just-wanna-rock-dub-scdler",
        "bpm": 84,
        "singer": "femme"
    },
    {
        "fileName": "lessons-scdler",
        "bpm": 135,
        "singer": "femme"
    },
    {
        "fileName": "lily-allen-smile-kryphon-bootleg-scdler",
        "bpm": 107,
        "singer": "femme"
    },
    {
        "fileName": "living-my-life-golden-feat.jill-scott-danny-byrd-remix-scdler",
        "bpm": 152,
        "singer": "femme"
    },
    {
        "fileName": "mph-kali-brooke-f1rst-x-nova-flip-scdler",
        "bpm": 131,
        "singer": "femme"
    },
    {
        "fileName": "mr.belt-amp-wezol-homeless-out-now-scdler",
        "bpm": 120,
        "singer": "femme"
    },
    {
        "fileName": "notion-dy-na-mi-tee-dub-dance-dubs-005-scdler",
        "bpm": 167,
        "singer": "femme"
    },
    {
        "fileName": "notion-temperature-dub-dance-dubs-002-scdler",
        "bpm": 135,
        "singer": "femme"
    },
    {
        "fileName": "nov-wait-stop-wait-scdler",
        "bpm": 163,
        "singer": "femme"
    },
    {
        "fileName": "oden-amp-fatzo-x-camden-cox-lady-love-extended-mix-scdler",
        "bpm": 111,
        "singer": "femme"
    },
    {
        "fileName": "og-wow-window-kid-scdler",
        "bpm": 132,
        "singer": "femme"
    },
    {
        "fileName": "on-my-ones-request-01-bass-request-scdler",
        "bpm": 133,
        "singer": "femme"
    },
    {
        "fileName": "on-my-ones-request-01-bass-request-scdler",
        "bpm": 133,
        "singer": "femme"
    },
    {
        "fileName": "pasilda-knee-deep-mix-scdler",
        "bpm": 86,
        "singer": "femme"
    },
    {
        "fileName": "shaggy-it-wasn-39-t-me-crash-amp-burn-mix-scdler",
        "bpm": 144,
        "singer": "femme"
    },
    {
        "fileName": "shella-verse-dub-scdler",
        "bpm": 134,
        "singer": "femme"
    },
    {
        "fileName": "show-me-scdler",
        "bpm": 128,
        "singer": "femme"
    },
    {
        "fileName": "sick-of-the-chatter-scdler",
        "bpm": 140,
        "singer": "femme"
    },
    {
        "fileName": "sleeping-alone-feat.poppy-baskcomb-scdler",
        "bpm": 142,
        "singer": "femme"
    },
    {
        "fileName": "sprinter-dub-scdler",
        "bpm": 131,
        "singer": "femme"
    },
    {
        "fileName": "still-sleepless-scdler",
        "bpm": 126,
        "singer": "femme"
    },
    {
        "fileName": "talking-scdler",
        "bpm": 135,
        "singer": "femme"
    },
    {
        "fileName": "think-about-you-feat.cj-pandit-scdler",
        "bpm": 164,
        "singer": "femme"
    },
    {
        "fileName": "u-could-be-mine-feat.catching-cairo-scdler",
        "bpm": 157,
        "singer": "femme"
    },
    {
        "fileName": "warrior-salute-remix-feat.sg-lewis-scdler",
        "bpm": 135,
        "singer": "femme"
    }
]